{
  "name": "Analyse_flights_dly",
  "category": "Machine Learning",
  "description": "analysing the flights delay",
  "nodes": [
    {
      "id": "1",
      "name": "DatasetStructured",
      "type": "dataset",
      "nodeClass": "fire.nodes.dataset.NodeDatasetStructured",
      "x": "18px",
      "y": "388.641px",
      "fields": [
        {
          "name": "dataset",
          "value": "2ff32692-9b3c-49de-91a7-401daf2590c1",
          "widget": "dataset",
          "title": "Dataset",
          "description": "Selected Dataset",
          "optionsMap": {
            "2ff32692-9b3c-49de-91a7-401daf2590c1": "flights_delay",
            "3d045ee1-7125-48b6-afeb-b26bae9cc47d": "KidneyLabResults",
            "bf506cf2-7f65-48cf-9e33-1411177c9bfd": "music",
            "ecf80851-4d96-4d7a-91ef-dfa8fe8937ee": "Housing",
            "429086c5-3e60-4fa1-9b6d-93c9d093ee48": "KindeyEgfrDerived",
            "b57c52b1-064a-4899-a075-20286ae7dde6": "ParquetFile",
            "4e9387d5-6a14-4961-858e-15ec72787dfa": "Churn Prediction",
            "697b0419-9fd2-485b-b999-b8125c63e773": "KidneyCdrFinding",
            "6fe6f5ec-5dca-453f-8f51-af31a96ebf63": "titanic_dat_train",
            "663c2be6-d2c0-4461-b20e-13d8353d0b9e": "PeopleParquet",
            "d8a1a0b1-93b8-4096-ab95-8e3a02d65263": "Ratings",
            "a610f2d8-59f9-471f-8576-e3a2b49ab369": "HIVE sample_07",
            "7fff0810-eb50-4b7e-8c9a-a55dcc2578f3": "Avazu",
            "a4ca862a-4127-449d-a7e0-c2fffd69fc14": "Cars",
            "033a08ff-fc0c-44cf-b713-1f4be7465834": "Omniture Products",
            "b4a7dc88-5ce0-41d9-bac0-93caa08b98e7": "datetimesample",
            "3c32dd3c-2464-4c60-8f1a-7bf3552aef04": "Omniture",
            "883dd363-f832-4c6a-8681-0dffc8ab638a": "Transaction dataset",
            "6fe6f5ec-5dca-453f-8f51-af33a96ebf63": "titanic_dat_train",
            "51273c4b-a101-43b5-94ca-06a928a0ea97": "Omniture Users",
            "6be87dab-55ab-4738-9fa6-97d8de4bd5r3": "spam1",
            "6be87dab-55ab-4738-9fa6-97d8de4bd5f3": "spam"
          },
          "required": false
        }
      ]
    },
    {
      "id": "2",
      "name": "PrintNRows",
      "description": "Prints the specified number of records in the DataFrame",
      "type": "transform",
      "nodeClass": "fire.nodes.util.NodePrintFirstNRows",
      "x": "46px",
      "y": "249.641px",
      "fields": [
        {
          "name": "n",
          "value": "10",
          "widget": "textfield",
          "title": "Num Rows to Print",
          "required": false
        }
      ]
    },
    {
      "id": "3",
      "name": "CastColumnType",
      "description": "This node creates a new DataFrame by casting input columns with input data types",
      "type": "transform",
      "nodeClass": "fire.nodes.etl.NodeCastColumnType",
      "x": "58px",
      "y": "85.6406px",
      "fields": [
        {
          "name": "colNames",
          "value": "[\"CRS_DEP_TIME\",\"CRS_ARR_TIME\",\"CRS_ELAPSED_TIME\"]",
          "widget": "variables",
          "title": "Columns",
          "description": "Columns to be casted to new data type",
          "optionsMap": {},
          "required": false
        },
        {
          "name": "outputTypes",
          "value": "double",
          "widget": "textfield",
          "title": "New Data Types",
          "description": "New data types separated by space",
          "required": false
        }
      ]
    },
    {
      "id": "4",
      "name": "CastColumnType",
      "description": "This node creates a new DataFrame by casting input columns with input data types",
      "type": "transform",
      "nodeClass": "fire.nodes.etl.NodeCastColumnType",
      "x": "278px",
      "y": "278.656px",
      "fields": [
        {
          "name": "colNames",
          "value": "[\"DAY_OF_MONTH\",\"DAY_OF_WEEK\"]",
          "widget": "variables",
          "title": "Columns",
          "description": "Columns to be casted to new data type",
          "optionsMap": {},
          "required": false
        },
        {
          "name": "outputTypes",
          "value": "string",
          "widget": "textfield",
          "title": "New Data Types",
          "description": "New data types separated by space",
          "required": false
        }
      ]
    },
    {
      "id": "5",
      "name": "StringIndexer",
      "description": "StringIndexer encodes a string column of labels to a column of label indices",
      "type": "ml-transformer",
      "nodeClass": "fire.nodes.ml.NodeStringIndexer",
      "x": "331px",
      "y": "62.6406px",
      "fields": [
        {
          "name": "handleInvalid",
          "value": "skip",
          "widget": "array",
          "title": "Handle Invalid",
          "description": "Invalid entries to be skipped or thrown error",
          "optionsArray": [
            "skip",
            "error"
          ],
          "required": false
        },
        {
          "name": "inputCols",
          "value": "[\"DAY_OF_MONTH\",\"DAY_OF_WEEK\",\"CARRIER\",\"TAIL_NUM\",\"FL_NUM\",\"ORIGIN_AIRPORT_ID\",\"ORIGIN\",\"DEST_AIRPORT_ID\",\"DEST\",\"CRS_DEP_TIME\",\"DEP_TIME\",\"DEP_DELAY_NEW\",\"CRS_ARR_TIME\",\"ARR_TIME\",\"ARR_DELAY_NEW\",\"CRS_ELAPSED_TIME\",\"DISTANCE\"]",
          "widget": "variables_map",
          "title": "Input Columns",
          "description": "Column containing labels",
          "required": false
        },
        {
          "name": "outputCols",
          "value": "[\"DAY_OF_MONTH_INDEX\",\"DAY_OF_WEEK_INDEX\",\"CARRIER_INDEX\",\"\",\"\",\"ORIGIN_AIRPORT_ID_INDEX\",\"\",\"DEST_AIRPORT_ID_INDEX\",\"\",\"\",\"\",\"\",\"\",\"\",\"\",\"\",\"\"]",
          "widget": "variables_map_edit",
          "title": "Output Columns",
          "description": "Output  columns",
          "required": false
        }
      ]
    },
    {
      "id": "6",
      "name": "PrintNRows",
      "description": "Prints the specified number of records in the DataFrame",
      "type": "transform",
      "nodeClass": "fire.nodes.util.NodePrintFirstNRows",
      "x": "630px",
      "y": "68.6406px",
      "fields": [
        {
          "name": "n",
          "value": "10",
          "widget": "textfield",
          "title": "Num Rows to Print",
          "required": false
        }
      ]
    },
    {
      "id": "7",
      "name": "SQL",
      "description": "This node runs the given SQL on the incoming DataFrame",
      "type": "transform",
      "nodeClass": "fire.nodes.etl.NodeSQL",
      "x": "722px",
      "y": "230.656px",
      "fields": [
        {
          "name": "tempTable",
          "value": "fire_temp_table",
          "widget": "textfield",
          "title": "Temp Table",
          "description": "Temp Table Name to be used",
          "required": false
        },
        {
          "name": "sql",
          "value": "select fire_temp_table.* , case  when fire_temp_table.DEP_DELAY_NEW > 40 then 1.0 else 0.0 END as label from fire_temp_table",
          "widget": "textarea_large",
          "title": "SQL",
          "description": "SQL to be run",
          "required": false
        },
        {
          "name": "columns",
          "value": "DAY_OF_MONTH DAY_OF_WEEK CARRIER TAIL_NUM FL_NUM ORIGIN_AIRPORT_ID ORIGIN DEST_AIRPORT_ID DEST CRS_DEP_TIME DEP_TIME DEP_DELAY_NEW CRS_ARR_TIME ARR_TIME ARR_DELAY_NEW CRS_ELAPSED_TIME DISTANCE DAY_OF_MONTH_INDEX DAY_OF_WEEK_INDEX CARRIER_INDEX ORIGIN_AIRPORT_ID_INDEX DEST_AIRPORT_ID_INDEX label",
          "widget": "textarea_small",
          "title": "SQL Output Column Names separated by space",
          "description": "New Output Columns of the SQL",
          "required": false
        },
        {
          "name": "columnTypes",
          "value": "string string string string int int string int string double int int double int int double int double double double double double double",
          "widget": "textarea_small",
          "title": "SQL Output Column Types separated by space",
          "description": "Data Type of the Output Columns",
          "required": false
        }
      ]
    },
    {
      "id": "8",
      "name": "PrintNRows",
      "description": "Prints the specified number of records in the DataFrame",
      "type": "transform",
      "nodeClass": "fire.nodes.util.NodePrintFirstNRows",
      "x": "527px",
      "y": "344.656px",
      "fields": [
        {
          "name": "n",
          "value": "10",
          "widget": "textfield",
          "title": "Num Rows to Print",
          "required": false
        }
      ]
    }
  ],
  "edges": [
    {
      "source": "1",
      "target": "2",
      "id": 1
    },
    {
      "source": "2",
      "target": "3",
      "id": 2
    },
    {
      "source": "3",
      "target": "4",
      "id": 3
    },
    {
      "source": "4",
      "target": "5",
      "id": 4
    },
    {
      "source": "5",
      "target": "6",
      "id": 5
    },
    {
      "source": "6",
      "target": "7",
      "id": 6
    },
    {
      "source": "7",
      "target": "8",
      "id": 7
    }
  ]
}